[{"month": "January", "precipitation": "43.6", "city": "hamilton"}, {"month": "February", "precipitation": "29.2", "city": "hamilton"}, {"month": "March", "precipitation": "35.2", "city": "hamilton"}, {"month": "April", "precipitation": "51", "city": "hamilton"}, {"month": "May", "precipitation": "50.2", "city": "hamilton"}, {"month": "June", "precipitation": "43.3", "city": "hamilton"}, {"month": "July", "precipitation": "44.7", "city": "hamilton"}, {"month": "August", "precipitation": "34.3", "city": "hamilton"}, {"month": "September", "precipitation": "39.9", "city": "hamilton"}, {"month": "October", "precipitation": "47.9", "city": "hamilton"}, {"month": "November", "precipitation": "37.8", "city": "hamilton"}, {"month": "December", "precipitation": "43.8", "city": "hamilton"}]